aiobook/__init__.py
aiobook/core/__init__.py
aiobook/core/aiobook.py
aiobook/core/facebook/__init__.py
aiobook/core/facebook/messenger.py
aiobook/core/facebook/handler/__init__.py
aiobook/core/facebook/handler/events.py
aiobook/core/facebook/handler/handler.py
aiobook/core/facebook/types/__init__.py
aiobook/core/facebook/types/buttons.py
aiobook/core/facebook/types/elements.py
aiobook/core/facebook/types/quick_replies.py
aiobook/core/facebook/types/send_api.py
aiobook/core/facebook/types/templates.py
aiobook-0.1.2.dist-info/LICENSE
aiobook-0.1.2.dist-info/METADATA
aiobook-0.1.2.dist-info/WHEEL
aiobook-0.1.2.dist-info/top_level.txt
aiobook-0.1.2.dist-info/RECORD
